kv_flask_hammer/__init__.py
kv_flask_hammer/config/__init__.py
kv_flask_hammer/config/app.py
kv_flask_hammer/config/jobs.py
kv_flask_hammer/config/logs.py
kv_flask_hammer/config/middleware.py
kv_flask_hammer/config/misc.py
kv_flask_hammer/config/observ.py
kv_flask_hammer/config/views.py
kv_flask_hammer/config_interface.py
kv_flask_hammer/constants.py
kv_flask_hammer/exceptions.py
kv_flask_hammer/gunicorn_app/__init__.py
kv_flask_hammer/gunicorn_app/gunicorn_funcs.py
kv_flask_hammer/jobs/__init__.py
kv_flask_hammer/logger.py
kv_flask_hammer/main.py
kv_flask_hammer/middleware/__init__.py
kv_flask_hammer/observ/__init__.py
kv_flask_hammer/observ/metrics.py
kv_flask_hammer/observ/traces.py
kv_flask_hammer/responses.py
kv_flask_hammer/utils/__init__.py
kv_flask_hammer/utils/application.py
kv_flask_hammer/utils/context.py
kv_flask_hammer/utils/converters.py
kv_flask_hammer/utils/metrics/__init__.py
kv_flask_hammer/utils/metrics/default.py
kv_flask_hammer/utils/metrics/registry.py
kv_flask_hammer/utils/middleware.py
kv_flask_hammer/utils/responses.py
kv_flask_hammer/utils/scheduler.py
kv_flask_hammer/utils/views.py
kv_flask_hammer/views/__init__.py
kv_flask_hammer/views/healthz.py
kv_flask_hammer/views/meta.py
kv_flask_hammer-0.2.7.dist-info/LICENSE
kv_flask_hammer-0.2.7.dist-info/METADATA
kv_flask_hammer-0.2.7.dist-info/WHEEL
kv_flask_hammer-0.2.7.dist-info/RECORD
