Metadata-Version: 2.3
Name: kv-flask-hammer
Version: 0.2.7
Summary: Flask-Hammer - For when every problem looks like a nail.
License: MIT
Author: Rob Voigt
Author-email: code@ravoigt.com
Requires-Python: >=3.11,<4.0
Classifier: License :: OSI Approved :: MIT License
Classifier: Programming Language :: Python :: 3
Classifier: Programming Language :: Python :: 3.11
Classifier: Programming Language :: Python :: 3.12
Classifier: Programming Language :: Python :: 3.13
Requires-Dist: flask (>=3.1.1,<4.0.0)
Requires-Dist: flask-apscheduler (>=1.13.1,<2.0.0)
Requires-Dist: flask-http-middleware (>=0.4.4,<0.5.0)
Requires-Dist: gunicorn (>=23.0.0,<24.0.0)
Requires-Dist: jinja2 (>=3.1.6,<4.0.0)
Requires-Dist: kvcommon[flask,metrics,traces] (>=0.4.4,<0.5.0)
Requires-Dist: opentelemetry-exporter-otlp
Requires-Dist: opentelemetry-instrumentation-flask
Requires-Dist: opentelemetry-instrumentation-logging
Requires-Dist: prometheus-client (>=0.20.0,<0.21.0)
Requires-Dist: prometheus-flask-exporter (>=0.23.1,<0.24.0)
Requires-Dist: protobuf (>=5.29.5)
Requires-Dist: requests
Requires-Dist: toml (>=0.10.2,<0.11.0)
Project-URL: Homepage, https://github.com/RAVoigt/kv-flask-hammer
Project-URL: Repository, https://github.com/RAVoigt/kv-flask-hammer
